primarch/__init__.py
primarch/categories.py
primarch/coverage.py
primarch/loading.py
primarch/transforms.py
primarch/plots/__init__.py
primarch/plots/colors.py
primarch/plots/lineplots.py
primarch/plots/treemaps.py
primarch-0.1.0.dist-info/WHEEL
primarch-0.1.0.dist-info/METADATA
primarch-0.1.0.dist-info/RECORD
